stat_arb_tools/__init__.py
stat_arb_tools/adf.py
stat_arb_tools/beta.py
stat_arb_tools/exceptions.py
stat_arb_tools/kellycritereon.py
stat_arb_tools/sigma.py
stat_arb_tools/spread.py
stat_arb_tools/stoploss.py
stat_arb_tools/znorm.py
stat_arb_tools-0.0.5.dist-info/LICENSE
stat_arb_tools-0.0.5.dist-info/METADATA
stat_arb_tools-0.0.5.dist-info/WHEEL
stat_arb_tools-0.0.5.dist-info/top_level.txt
stat_arb_tools-0.0.5.dist-info/RECORD
