Metadata-Version: 2.1
Name: stat-arb-tools
Version: 0.0.5
Summary: This package provides statistics arbitrage tools for traders
Home-page: https://github.com/devnull-capital/stat_arb_tools
Author: Adam Hanna
Author-email: ahanna@mba2016.hbs.edu
License: UNKNOWN
Platform: UNKNOWN
Classifier: Programming Language :: Python :: 3
Classifier: License :: OSI Approved :: MIT License
Classifier: Operating System :: OS Independent
Requires-Dist: scipy
Requires-Dist: numpy
Requires-Dist: statsmodels
Requires-Dist: numpydoc
